python_v2ray/__init__.py
python_v2ray/api_client.py
python_v2ray/config_parser.py
python_v2ray/core.py
python_v2ray/downloader.py
python_v2ray/exceptions.py
python_v2ray/hysteria_manager.py
python_v2ray/models.py
python_v2ray/process_manager.py
python_v2ray/speed_tester.py
python_v2ray/tester.py
python_v2ray/protos/__init__.py
python_v2ray/protos/app/__init__.py
python_v2ray/protos/app/stats/command/command.proto
python_v2ray/protos/app/stats/command/command_pb2.py
python_v2ray/protos/app/stats/command/command_pb2_grpc.py
python_v2ray/protos/common/serial/typed_message.proto
python_v2ray-0.1.8.dist-info/licenses/LICENSE
python_v2ray-0.1.8.dist-info/METADATA
python_v2ray-0.1.8.dist-info/WHEEL
python_v2ray-0.1.8.dist-info/top_level.txt
python_v2ray-0.1.8.dist-info/RECORD
