Metadata-Version: 2.4
Name: python_v2ray
Version: 0.1.8
Summary: A powerful, high-level Python wrapper for managing and testing V2Ray/Xray-core and Hysteria clients.
Author-email: arshiacomplus <arshiacomplus@gmail.com>
License: GPL-3.0-only
Classifier: Programming Language :: Python :: 3
Classifier: License :: OSI Approved :: GNU General Public License v3 (GPLv3)
Classifier: Operating System :: OS Independent
Classifier: Intended Audience :: Developers
Classifier: Topic :: Internet :: Proxy Servers
Classifier: Topic :: System :: Networking
Requires-Python: >=3.8
License-File: LICENSE
Requires-Dist: requests[socks]>=2.25.0
Requires-Dist: grpcio>=1.40.0
Requires-Dist: protobuf>=3.19.0
Dynamic: license-file
